{
    "batting_averages": [
        {
            "": "Tests",
            "100": "1",
            "50": "0",
            "6s": "1",
            "Ave": "25.50",
            "Ct": "5",
            "HS": "104*",
            "Inns": "9",
            "Mat": "6",
            "NO": "1",
            "Runs": "204",
            "St": "0"
        },
        {
            "": "First-class",
            "100": "56",
            "50": "160",
            "6s": "",
            "Ave": "33.73",
            "Ct": "760",
            "HS": "170",
            "Inns": "1078",
            "Mat": "620",
            "NO": "125",
            "Runs": "32150",
            "St": "0"
        },
        {
            "": "List A",
            "100": "0",
            "50": "5",
            "6s": "",
            "Ave": "23.29",
            "Ct": "22",
            "HS": "87",
            "Inns": "52",
            "Mat": "55",
            "NO": "5",
            "Runs": "1095",
            "St": "0"
        }
    ],
    "bowling_averages": [
        {
            "": "Tests",
            "10": "0",
            "4w": "0",
            "5w": "0",
            "Ave": "-",
            "BBI": "-",
            "BBM": "-",
            "Balls": "24",
            "Econ": "3.00",
            "Inns": "1",
            "Mat": "6",
            "Runs": "12",
            "SR": "-",
            "Wkts": "0"
        },
        {
            "": "First-class",
            "10": "0",
            "4w": "",
            "5w": "1",
            "Ave": "46.07",
            "BBI": "5/64",
            "BBM": "",
            "Balls": "8414",
            "Econ": "2.59",
            "Inns": "",
            "Mat": "620",
            "Runs": "3640",
            "SR": "106.5",
            "Wkts": "79"
        },
        {
            "": "List A",
            "10": "0",
            "4w": "0",
            "5w": "0",
            "Ave": "13.00",
            "BBI": "2/26",
            "BBM": "2/26",
            "Balls": "24",
            "Econ": "6.50",
            "Inns": "",
            "Mat": "55",
            "Runs": "26",
            "SR": "12.0",
            "Wkts": "2"
        }
    ],
    "latest_articles": [
        "http://www.espncricinfo.com/magazine/content/story/527747.html",
        "http://www.espncricinfo.com/wisdenalmanack/content/story/353626.html",
        "http://www.espncricinfo.com/wisdencricketer/content/story/302334.html",
        "http://www.espncricinfo.com/england/content/story/292360.html",
        "http://www.espncricinfo.com/wisdencricketer/content/story/229621.html",
        "http://www.espncricinfo.com/ci/content/story/news.html?object=17037"
    ],
    "latest_photos": [
        "http://p.imgci.com/db/PICTURES/DB/062004/053160.icon.jpg",
        "http://p.imgci.com/db/PICTURES/DB/062004/053160.icon.jpg",
        "http://p.imgci.com/db/PICTURES/DB/062004/053160.icon.jpg"
    ],
    "personal_info": {
        "Batting style": [
            "Right-hand bat"
        ],
        "Born": [
            "\nMarch 10, 1928, Bedminster, Somerset "
        ],
        "Bowling style": [
            "Right-arm medium"
        ],
        "Died": [
            "April 25, 2007, Bristol (aged 79 years 46 days) "
        ],
        "Full name": [
            "Clement Arthur Milton"
        ],
        "Major teams": [
            "England,",
            "Gloucestershire"
        ]
    },
    "profile_info": [
        null
    ],
    "recent_matches": [
        {},
        {}
    ]
}