{
    "batting_averages": [
        {
            "": "Tests",
            "100": "0",
            "4s": "3",
            "50": "0",
            "6s": "0",
            "Ave": "18.00",
            "BF": "89",
            "Ct": "0",
            "HS": "25",
            "Inns": "2",
            "Mat": "1",
            "NO": "0",
            "Runs": "36",
            "SR": "40.44",
            "St": "0"
        },
        {
            "": "First-class",
            "100": "25",
            "4s": "",
            "50": "78",
            "6s": "",
            "Ave": "32.39",
            "BF": "",
            "Ct": "182",
            "HS": "202*",
            "Inns": "512",
            "Mat": "304",
            "NO": "56",
            "Runs": "14773",
            "SR": "",
            "St": "0"
        },
        {
            "": "List A",
            "100": "8",
            "4s": "",
            "50": "38",
            "6s": "",
            "Ave": "29.36",
            "BF": "",
            "Ct": "119",
            "HS": "142",
            "Inns": "283",
            "Mat": "318",
            "NO": "36",
            "Runs": "7252",
            "SR": "",
            "St": "0"
        }
    ],
    "bowling_averages": [
        {
            "": "Tests",
            "10": "-",
            "4w": "-",
            "5w": "-",
            "Ave": "-",
            "BBI": "-",
            "BBM": "-",
            "Balls": "-",
            "Econ": "-",
            "Inns": "-",
            "Mat": "1",
            "Runs": "-",
            "SR": "-",
            "Wkts": "-"
        },
        {
            "": "First-class",
            "10": "1",
            "4w": "",
            "5w": "11",
            "Ave": "32.55",
            "BBI": "7/44",
            "BBM": "",
            "Balls": "23018",
            "Econ": "3.35",
            "Inns": "",
            "Mat": "304",
            "Runs": "12890",
            "SR": "58.1",
            "Wkts": "396"
        },
        {
            "": "List A",
            "10": "0",
            "4w": "4",
            "5w": "3",
            "Ave": "26.40",
            "BBI": "6/33",
            "BBM": "6/33",
            "Balls": "9216",
            "Econ": "4.64",
            "Inns": "",
            "Mat": "318",
            "Runs": "7130",
            "SR": "34.1",
            "Wkts": "270"
        }
    ],
    "latest_articles": [
        "http://www.espncricinfo.com/engvnz/content/story/347483.html",
        "http://www.espncricinfo.com/england/content/story/297222.html",
        "http://www.espncricinfo.com/england/content/story/243228.html",
        "http://www.espncricinfo.com/westindies/content/story/138840.html",
        "http://www.espncricinfo.com/magazine/content/story/138097.html",
        "http://www.espncricinfo.com/ci/content/story/news.html?object=20359"
    ],
    "latest_photos": [
        "http://p.imgci.com/db/PICTURES/CMS/244300/244387.icon.jpg",
        "http://p.imgci.com/db/PICTURES/CMS/244300/244387.icon.jpg",
        "http://p.imgci.com/db/PICTURES/CMS/244300/244387.icon.jpg"
    ],
    "personal_info": {
        "Batting style": [
            "Right-hand bat"
        ],
        "Born": [
            "\nMarch 14, 1965, Stebbing, Essex "
        ],
        "Bowling style": [
            "Right-arm medium"
        ],
        "Current age": [
            "53 years 157 days"
        ],
        "Full name": [
            "John Patrick Stephenson"
        ],
        "Major teams": [
            "England,",
            "Boland,",
            "Essex,",
            "Hampshire,",
            "Marylebone Cricket Club"
        ]
    },
    "profile_info": [
        null
    ],
    "recent_matches": [
        {
            "Bat & Bowl": "1/18",
            "Ground": "Arundel",
            "Match Date": "5 Jun 2018",
            "Opposition": "v Aboriginal",
            "Scorecard": "Other T20",
            "Team": "M.C.C."
        },
        {
            "Bat & Bowl": "1",
            "Ground": "Arundel",
            "Match Date": "5 Jun 2018",
            "Opposition": "v Aboriginal",
            "Scorecard": "Other T20",
            "Team": "M.C.C."
        },
        {
            "Bat & Bowl": "1/39",
            "Ground": "Lord's",
            "Match Date": "21 Apr 2011",
            "Opposition": "v Scotland",
            "Scorecard": "Other OD",
            "Team": "M.C.C."
        },
        {
            "Bat & Bowl": "2/42",
            "Ground": "Arundel",
            "Match Date": "27 Apr 2008",
            "Opposition": "v N Zealanders",
            "Scorecard": "Other",
            "Team": "M.C.C."
        },
        {
            "Bat & Bowl": "0/23",
            "Ground": "Lord's",
            "Match Date": "21 Apr 2008",
            "Opposition": "v Scotland",
            "Scorecard": "Other OD",
            "Team": "M.C.C."
        },
        {
            "Bat & Bowl": "51, 3/39",
            "Ground": "Lord's",
            "Match Date": "7 Jun 2007",
            "Opposition": "v European XI",
            "Scorecard": "Other",
            "Team": "M.C.C."
        },
        {
            "Bat & Bowl": "2/36",
            "Ground": "Rotterdam",
            "Match Date": "29 Jun 2006",
            "Opposition": "v European XI",
            "Scorecard": "Other OD",
            "Team": "M.C.C."
        },
        {
            "Bat & Bowl": "2/37",
            "Ground": "Wormsley",
            "Match Date": "2 May 2006",
            "Opposition": "v Sri Lankans",
            "Scorecard": "Other",
            "Team": "Sir Paul Getty's XI"
        },
        {
            "Bat & Bowl": "3/6, 1, 0/28, 0",
            "Ground": "Lord's",
            "Match Date": "14 Apr 2006",
            "Opposition": "v Notts",
            "Scorecard": "FC",
            "Team": "M.C.C."
        }
    ]
}