{
    "batting_averages": [
        {
            "": "Tests",
            "100": "0",
            "4s": "",
            "50": "0",
            "6s": "0",
            "Ave": "5.84",
            "Ct": "2",
            "HS": "17",
            "Inns": "19",
            "Mat": "13",
            "NO": "6",
            "Runs": "76",
            "St": "0"
        },
        {
            "": "First-class",
            "100": "0",
            "4s": "",
            "50": "2",
            "6s": "",
            "Ave": "8.50",
            "Ct": "119",
            "HS": "81",
            "Inns": "382",
            "Mat": "371",
            "NO": "110",
            "Runs": "2314",
            "St": "0"
        },
        {
            "": "List A",
            "100": "0",
            "4s": "0",
            "50": "0",
            "6s": "0",
            "Ave": "1.00",
            "Ct": "0",
            "HS": "1",
            "Inns": "1",
            "Mat": "1",
            "NO": "0",
            "Runs": "1",
            "St": "0"
        }
    ],
    "bowling_averages": [
        {
            "": "Tests",
            "10": "0",
            "4w": "2",
            "5w": "1",
            "Ave": "22.51",
            "BBI": "6/36",
            "BBM": "9/86",
            "Balls": "2662",
            "Econ": "1.97",
            "Inns": "26",
            "Mat": "13",
            "Runs": "878",
            "SR": "68.2",
            "Wkts": "39"
        },
        {
            "": "First-class",
            "10": "13",
            "4w": "",
            "5w": "70",
            "Ave": "19.04",
            "BBI": "9/17",
            "BBM": "",
            "Balls": "62522",
            "Econ": "2.42",
            "Inns": "",
            "Mat": "371",
            "Runs": "25260",
            "SR": "47.1",
            "Wkts": "1326"
        },
        {
            "": "List A",
            "10": "0",
            "4w": "0",
            "5w": "0",
            "Ave": "11.66",
            "BBI": "3/35",
            "BBM": "3/35",
            "Balls": "90",
            "Econ": "2.33",
            "Inns": "",
            "Mat": "1",
            "Runs": "35",
            "SR": "30.0",
            "Wkts": "3"
        }
    ],
    "latest_articles": [
        "http://www.espncricinfo.com/wisdenalmanack/content/story/596971.html",
        "http://www.espncricinfo.com/england/content/story/506536.html",
        "http://www.espncricinfo.com/ci/content/story/129082.html",
        "http://www.espncricinfo.com/wisdenalmanack/content/story/154589.html"
    ],
    "latest_photos": [
        "http://p.imgci.com/db/PICTURES/CMS/54700/54751.icon.jpg",
        "http://p.imgci.com/db/PICTURES/CMS/54700/54751.icon.jpg",
        "http://p.imgci.com/db/PICTURES/CMS/54700/54751.icon.jpg"
    ],
    "personal_info": {
        "Batting style": [
            "Right-hand bat"
        ],
        "Born": [
            "\nOctober 25, 1929, Wallington, Surrey "
        ],
        "Bowling style": [
            "Right-arm fast"
        ],
        "Died": [
            "March 15, 2011 (aged 81 years 141 days) "
        ],
        "Full name": [
            "Peter James Loader"
        ],
        "Major teams": [
            "England,",
            "Surrey,",
            "Western Australia"
        ],
        "Other": [
            "Umpire, Commentator"
        ]
    },
    "profile_info": [
        null
    ],
    "recent_matches": [
        {},
        {},
        {},
        {},
        {},
        {},
        {}
    ]
}